zion_computer-0.1.28.dist-info/METADATA
zion_computer-0.1.28.dist-info/WHEEL
zion/_zion.pyi
zion/__init__.py
zion/py.typed
zion/_zion.abi3.so
zion_computer-0.1.28.dist-info/RECORD
